applying/__init__.py
applying/cloudformation/__init__.py
applying/cloudformation/project.py
applying_cli-0.0.3.dist-info/LICENSE.txt
applying_cli-0.0.3.dist-info/METADATA
applying_cli-0.0.3.dist-info/WHEEL
applying_cli-0.0.3.dist-info/top_level.txt
applying_cli-0.0.3.dist-info/RECORD
