Metadata-Version: 2.1
Name: applying-cli
Version: 0.0.3
Summary: Command Line Interface for Applying projects
Home-page: https://www.google.com
Author: john velasquez
Author-email: javv.92@gmail.com
Project-URL: Bug Tracker, https://www.google.com
Classifier: Programming Language :: Python :: 3
Classifier: License :: OSI Approved :: MIT License
Classifier: Operating System :: OS Independent
Requires-Python: >=3.7
License-File: LICENSE.txt
